dqa_commonlib/__init__.py
dqa_commonlib/cmd_process.py
dqa_commonlib/configs.py
dqa_commonlib/deco.py
dqa_commonlib/emails.py
dqa_commonlib/mysql_db.py
dqa_commonlib-0.5.5.dist-info/DESCRIPTION.rst
dqa_commonlib-0.5.5.dist-info/METADATA
dqa_commonlib-0.5.5.dist-info/RECORD
dqa_commonlib-0.5.5.dist-info/WHEEL
dqa_commonlib-0.5.5.dist-info/metadata.json
dqa_commonlib-0.5.5.dist-info/top_level.txt
