Metadata-Version: 2.0
Name: dqa-commonlib
Version: 0.5.5
Summary: common script operations liabray about python
Home-page: https://github.com/xiaoyaoyuyi/python_package_test
Author: xiaoyaoyuyi
Author-email: 389105015@qq.com
License: MIT
Keywords: Just common library for Python
Platform: UNKNOWN
Classifier: Programming Language :: Python :: 2.7
Requires-Python: >=2.7
Requires-Dist: MySQL-python
